rasierwasser/LICENSE.txt
rasierwasser/__init__.py
rasierwasser/configuration/__init__.py
rasierwasser/configuration/main.py
rasierwasser/configuration/server.py
rasierwasser/configuration/storage.py
rasierwasser/helper/__init__.py
rasierwasser/helper/signing.py
rasierwasser/server/__init__.py
rasierwasser/server/data/base_index.html
rasierwasser/server/data/package_index.html
rasierwasser/server/fastapi/__init__.py
rasierwasser/server/fastapi/auth.py
rasierwasser/server/fastapi/fastapi.py
rasierwasser/service/__init__.py
rasierwasser/service/server.py
rasierwasser/storage/__init__.py
rasierwasser/storage/algebra.py
rasierwasser/storage/database/__init__.py
rasierwasser/storage/database/engine.py
rasierwasser/storage/database/model.py
rasierwasser/storage/validation.py
rasierwasser-0.1.13.dist-info/entry_points.txt
rasierwasser-0.1.13.dist-info/WHEEL
rasierwasser-0.1.13.dist-info/METADATA
rasierwasser-0.1.13.dist-info/RECORD
