Metadata-Version: 2.1
Name: rasierwasser
Version: 0.1.13
Summary: Simple pip repository server for internal usage
Home-page: https://github.com/voidpointercast/rasierwasser
License: GPLv3
Author: voidpointercast
Author-email: patrick.daniel.gress@gmail.com
Requires-Python: >=3.8
Classifier: License :: Other/Proprietary License
Classifier: Programming Language :: Python :: 3
Classifier: Programming Language :: Python :: 3.8
Classifier: Programming Language :: Python :: 3.9
Provides-Extra: mysql
Provides-Extra: oracle
Provides-Extra: pgsql
Requires-Dist: Flask (>=2.0.1,<3.0.0)
Requires-Dist: Jinja2 (>=3.0.1,<4.0.0)
Requires-Dist: PyYAML (>=5.4.1,<6.0.0)
Requires-Dist: SQLAlchemy (>=1.4.17,<2.0.0)
Requires-Dist: fastapi (>=0.65.1,<0.66.0)
Requires-Dist: pyOpenSSL (>=20.0.1,<21.0.0)
Requires-Dist: pydantic (>=1.8.2,<2.0.0)
Requires-Dist: requests (>=2.25.1,<3.0.0)
Requires-Dist: toml (>=0.10.2,<0.11.0)
Requires-Dist: uvicorn (>=0.14.0,<0.15.0)
Project-URL: Repository, https://github.com/voidpointercast/rasierwasser
